signhere/__init__.py
signhere/exceptions.py
signhere/utils.py
signhere-0.5.0.dist-info/LICENSE
signhere-0.5.0.dist-info/METADATA
signhere-0.5.0.dist-info/WHEEL
signhere-0.5.0.dist-info/RECORD
